owa/msgs/desktop/keyboard.py
owa/msgs/desktop/mouse.py
owa/msgs/desktop/screen.py
owa/msgs/desktop/window.py
owa_msgs-0.6.5.dist-info/METADATA
owa_msgs-0.6.5.dist-info/WHEEL
owa_msgs-0.6.5.dist-info/entry_points.txt
owa_msgs-0.6.5.dist-info/RECORD
