Metadata-Version: 2.4
Name: owa-msgs
Version: 0.6.5
Summary: Core message definitions for Open World Agents
License: MIT
Requires-Python: >=3.11
Requires-Dist: annotated-types
Requires-Dist: mediaref~=0.4.1
Requires-Dist: numpy>=2.0
Requires-Dist: opencv-python
Requires-Dist: owa-core==0.6.5
Requires-Dist: pydantic>=2.0
